{
  "db_name": "PostgreSQL",
  "query": "\n            SELECT title, text_content, html_content\n            FROM newsletter_issues\n            WHERE\n    newsletter_issue_id = $1 ",
  "describe": {
    "columns": [
      {
        "ordinal": 0,
        "name": "title",
        "type_info": "Text"
      },
      {
        "ordinal": 1,
        "name": "text_content",
        "type_info": "Text"
      },
      {
        "ordinal": 2,
        "name": "html_content",
        "type_info": "Text"
      }
    ],
    "parameters": {
      "Left": [
        "Uuid"
      ]
    },
    "nullable": [
      false,
      false,
      false
    ]
  },
  "hash": "5b08a55856d11982d00c31579cf2ef0be460d81bb3310bac98621e85c3ca1444"
}
